{
  "id": "other",
  "name": "その他",
  "tag": "一般モデル｜業種を特定しない中立前提",
  "note": "【想定モデルによる試算】特定業種に寄せない中立的な前提の概算です。実際の効果は業務内容・導入範囲により異なります。具体的な試算は貴社の実データをもとに別途ご提示します。",
  "categories": [
    {
      "key": "field",
      "label": "現場・実務",
      "sub": "日々の記録と報告の手間を減らす",
      "eyebrow": "現場・実務",
      "title": "日々の記録や報告に、\n時間を取られていませんか？",
      "lead": "作業内容のメモ、写真やファイルの整理、報告への転記。この作業が、現場50名ぶん積み重なっています。",
      "otherLabel": "やり直し・探しもの・漏れの回避（年間）",
      "otherHint": "報告のやり直しや資料の探し直しを減らした効果の目安。分からなければ0でも構いません。",
      "summary": "後始末の時間を、**本業に集中する時間**に変える。",
      "defaults": {
        "people": 50,
        "cases": 15,
        "minutes": 20,
        "reduction": 70,
        "wage": 3000,
        "other": 2000000,
        "initial": 2800000,
        "monthly": 220000
      }
    },
    {
      "key": "internal",
      "label": "内勤・作成",
      "sub": "資料作成と問い合わせ対応の手間を減らす",
      "eyebrow": "内勤・作成",
      "title": "定型の資料作りや問い合わせ対応に、\n時間を取られていませんか？",
      "lead": "定型資料の体裁整え、社内外からの照会対応、データの転記。この事務が、内勤20名ぶん積み重なっています。",
      "otherLabel": "転記・照会対応の削減（年間）",
      "otherHint": "差し戻しや同じ質問への対応を減らした効果の目安。分からなければ0でも構いません。",
      "summary": "繰り返し作業の時間を、**改善と顧客対応の時間**に変える。",
      "defaults": {
        "people": 20,
        "cases": 12,
        "minutes": 40,
        "reduction": 75,
        "wage": 3000,
        "other": 1500000,
        "initial": 2500000,
        "monthly": 200000
      }
    },
    {
      "key": "dashboard",
      "label": "管理・経営",
      "sub": "進捗と数字の食い違いを減らす",
      "eyebrow": "管理・経営",
      "title": "「現場はそう言ってない」の確認に、\n時間を取られていませんか？",
      "lead": "報告がバラバラに届き、振り分け・突合・確認に追われる。現場と内勤の食い違いを埋める作業が、管理職10名の判断を遅らせています。",
      "otherLabel": "認識のズレによる手戻り・トラブル対応の回避（年間）",
      "otherHint": "認識の食い違いから生まれるやり直しやクレーム対応を減らした効果の目安。経営への影響が大きい部分です。",
      "summary": "食い違いを正す時間を、**早く正しく決める時間**に変える。",
      "defaults": {
        "people": 10,
        "cases": 8,
        "minutes": 60,
        "reduction": 65,
        "wage": 4500,
        "other": 4000000,
        "initial": 2500000,
        "monthly": 200000
      }
    }
  ]
}
